README.md
setup.py
sklearn_pipeline_utils/__init__.py
sklearn_pipeline_utils/skutils.py
sklearn_pipeline_utils.egg-info/PKG-INFO
sklearn_pipeline_utils.egg-info/SOURCES.txt
sklearn_pipeline_utils.egg-info/dependency_links.txt
sklearn_pipeline_utils.egg-info/not-zip-safe
sklearn_pipeline_utils.egg-info/top_level.txt